Metadata-Version: 2.0
Name: histcensusgis
Version: 1.0.0a139
Summary: Tools for cleaning and geocoding full count census data (1900-1940)
Home-page: http://www.github.com/graziul/hist-census-gis
Author: Historical GIS Project, Spatial Structures in the Social Sciences, Brown University
Author-email: christopher_graziul@brown.edu
License: UNKNOWN
Platform: UNKNOWN
Classifier: Development Status :: 3 - Alpha
Classifier: License :: OSI Approved :: MIT License
Classifier: Programming Language :: Python :: 2.7
Requires-Dist: Cython
Requires-Dist: pysal
Requires-Dist: openpyxl
Requires-Dist: pandas
Requires-Dist: xlrd
Requires-Dist: fiona
Requires-Dist: pyproj
Requires-Dist: geopandas
Requires-Dist: fuzzyset
Requires-Dist: paramiko
Requires-Dist: unicodecsv
Requires-Dist: dbf
Requires-Dist: argparse
Requires-Dist: fuzzywuzzy
Requires-Dist: netcdf4
